stactools/alos_dem/__init__.py
stactools/alos_dem/commands.py
stactools/alos_dem/constants.py
stactools/alos_dem/stac.py
stactools_alos_dem-0.1.2.dist-info/LICENSE
stactools_alos_dem-0.1.2.dist-info/METADATA
stactools_alos_dem-0.1.2.dist-info/WHEEL
stactools_alos_dem-0.1.2.dist-info/top_level.txt
stactools_alos_dem-0.1.2.dist-info/RECORD
