Metadata-Version: 2.1
Name: stactools-alos-dem
Version: 0.1.2
Summary: Create STAC items from ALOS Global Digital Surface Model data
Home-page: https://github.com/stactools-packages/alos-dem
Author: Pete Gadomski
Author-email: pete.gadomski@gmail.com
License: UNKNOWN
Project-URL: Documentation, https://stactools-alos-dem.readthedocs.io/en/latest/
Project-URL: Issues, https://github.com/stactools-packages/alos-dem/issues
Keywords: stactools,pystac,catalog,STAC,ALOS,dem,elevation,raster
Platform: UNKNOWN
Classifier: Development Status :: 4 - Beta
Classifier: License :: OSI Approved :: Apache Software License
Classifier: Programming Language :: Python :: 3.7
Classifier: Programming Language :: Python :: 3.8
Classifier: Programming Language :: Python :: 3.9
License-File: LICENSE
Requires-Dist: stactools (==0.2.1)
